{
  "default_threshold": 0.75,
  "invoice_number": {
    "min_confidence": 0.95,
    "review_on_breach": true,
    "fail_on_breach": true,
    "regulatory_required": false,
    "description": "Primary AP matching key."
  },
  "vendor_name": {
    "min_confidence": 0.93,
    "review_on_breach": true,
    "fail_on_breach": true,
    "regulatory_required": false,
    "description": "Vendor identity controls payment and duplicate detection."
  },
  "invoice_date": {
    "min_confidence": 0.9,
    "review_on_breach": true,
    "fail_on_breach": false,
    "regulatory_required": false,
    "description": "Invoice date supports payment terms and aging."
  },
  "total_amount": {
    "min_confidence": 0.95,
    "review_on_breach": true,
    "fail_on_breach": true,
    "regulatory_required": false,
    "description": "Total amount is the core payment control field."
  },
  "amount_due": {
    "min_confidence": 0.92,
    "review_on_breach": true,
    "fail_on_breach": false,
    "regulatory_required": false,
    "description": "Amount due determines payment amount after credits or partial payment."
  }
}
